amxmaintenance/__init__.py
amxmaintenance-0.0.4.dist-info/LICENSE
amxmaintenance-0.0.4.dist-info/METADATA
amxmaintenance-0.0.4.dist-info/WHEEL
amxmaintenance-0.0.4.dist-info/top_level.txt
amxmaintenance-0.0.4.dist-info/RECORD
