Metadata-Version: 2.1
Name: amxmaintenance
Version: 0.0.4
Summary: amx telnet info, firmware checks, logs, etc.
Home-page: https://github.com/logantv/amxmaintenance
Author: Logan Vaughn
License: UNKNOWN
Project-URL: Bug Tracker, https://github.com/logantv/amxmaintenance/issues
Platform: UNKNOWN
Classifier: Programming Language :: Python :: 3
Classifier: License :: OSI Approved :: MIT License
Classifier: Operating System :: OS Independent
Requires-Python: >=3.6
License-File: LICENSE
Requires-Dist: amxtelnet
Requires-Dist: amxlogs
Requires-Dist: exceltoamx
Requires-Dist: amxtoexcel
Requires-Dist: amxfirmware
